djt_og/__init__.py
djt_og/opengraph.py
djt_og/panel.py
djt_og/templates/debug/opengraph.html
djt_og_test/__init__.py
djt_og_test/test_og.py
djt_og-0.9.7.dist-info/METADATA
djt_og-0.9.7.dist-info/WHEEL
djt_og-0.9.7.dist-info/top_level.txt
djt_og-0.9.7.dist-info/RECORD
