Metadata-Version: 2.1
Name: djt-og
Version: 0.9.7
Summary: Panel for Django-debug-toolbar that displays OpenGraph metadata found in your HTML page.
Home-page: https://github.com/d9pouces/djt_og
Author: Matthieu Gallet
Author-email: github@19pouces.net
Maintainer: Matthieu Gallet
Maintainer-email: github@19pouces.net
License: CeCILL-B
Classifier: Development Status :: 5 - Production/Stable
Classifier: Framework :: Django :: 2.0
Classifier: Framework :: Django :: 2.1
Classifier: Framework :: Django :: 2.2
Classifier: Framework :: Django :: 3.0
Classifier: Framework :: Django :: 3.1
Classifier: License :: OSI Approved :: CEA CNRS Inria Logiciel Libre License, version 2.1 (CeCILL-2.1)
Classifier: Operating System :: MacOS :: MacOS X
Classifier: Operating System :: Microsoft :: Windows
Classifier: Operating System :: POSIX :: BSD
Classifier: Operating System :: POSIX :: Linux
Classifier: Operating System :: Unix
Classifier: Programming Language :: Python :: 3 :: Only
Classifier: Programming Language :: Python :: 3.5
Classifier: Programming Language :: Python :: 3.6
Classifier: Programming Language :: Python :: 3.7
Classifier: Programming Language :: Python :: 3.8
Classifier: Programming Language :: Python :: 3.9
Requires-Dist: beautifulsoup4
Requires-Dist: django
Requires-Dist: django-debug-toolbar
